verilator/mux21/mux21.v
module mux21(a,b,s,y);
  input   a,b,s;        // 声明3个wire型输入变量a,b,和s，其宽度为1位。
  output  y;           // 声明1个wire型输出变量y，其宽度为1位。

  assign  y = (~s&a)|(s&b);  // 实现电路的逻辑功能。

endmodule

verilator/mux21/obj_dir/dump.vcd
$version Generated by VerilatedVcd $end
$date Wed Mar 22 15:39:32 2023 $end
$timescale 1s $end

 $scope module TOP $end
  $var wire  1 # a $end
  $var wire  1 $ b $end
  $var wire  1 % s $end
  $var wire  1 & y $end
  $scope module mux21 $end
   $var wire  1 # a $end
   $var wire  1 $ b $end
   $var wire  1 % s $end
   $var wire  1 & y $end
  $upscope $end
 $upscope $end
$enddefinitions $end


#1
0#
0$
0%
0&
#2
1$
#3
1#
0$
1&
#4
1$
#5
0#
0$
1%
0&
#6
1$
1&
#7
1#
0$
0&
#8
1$
1&
