verilator/Fulladder1/Fulladder1.v
module Fulladder1(c,a,b,s,cip1);
  input   c,a,b; 
  output  s,cip1; 

  assign  s=(a^b)^c;
  assign  cip1=(a&b)|((a^b)&c);

endmodule

verilator/Fulladder1/obj_dir/dump.vcd
$version Generated by VerilatedVcd $end
$date Wed Apr 12 14:48:54 2023 $end
$timescale 1s $end

 $scope module TOP $end
  $var wire  1 $ a $end
  $var wire  1 % b $end
  $var wire  1 # c $end
  $var wire  1 ' cip1 $end
  $var wire  1 & s $end
  $scope module Fulladder1 $end
   $var wire  1 $ a $end
   $var wire  1 % b $end
   $var wire  1 # c $end
   $var wire  1 ' cip1 $end
   $var wire  1 & s $end
  $upscope $end
 $upscope $end
$enddefinitions $end


#1
0#
0$
0%
0&
0'
#2
1%
1&
#3
1$
0%
#4
1%
0&
1'
#5
1#
0$
0%
1&
0'
#6
1%
0&
1'
#7
1$
0%
#8
1%
1&
